abbts_blp/__init__.py
abbts_blp/dummy.py
abbts_blp/rgb/__init__.py
abbts_blp/rgb/rgb_fpga.py
abbts_blp/rgb/rgb_matrix.py
abbts_blp/rgb/__pycache__/__init__.cpython-311.pyc
abbts_blp/rgb/__pycache__/rgb_fpga.cpython-311.pyc
abbts_blp/rgb/__pycache__/rgb_matrix.cpython-311.pyc
abbts_blp-0.0.6.dist-info/LICENSE.txt
abbts_blp-0.0.6.dist-info/METADATA
abbts_blp-0.0.6.dist-info/WHEEL
abbts_blp-0.0.6.dist-info/top_level.txt
abbts_blp-0.0.6.dist-info/RECORD
