Metadata-Version: 2.1
Name: abbts-blp
Version: 0.0.6
Summary: abbts_blp
Home-page: https://github.com/p-d-h/abbts_blp
Author: Pascal Helfenstein
Author-email: pascal.helfenstein@abbts.ch
License: LICENSE.txt
Classifier: Development Status :: 4 - Beta
Classifier: Intended Audience :: Developers
Classifier: Topic :: Software Development :: Build Tools
Requires-Python: >=3.8
License-File: LICENSE.txt
Requires-Dist: pyserial (>=3.5)
Requires-Dist: Pillow (>=9.3)
